mlpipeline/__init__.py
mlpipeline/_cli.py
mlpipeline/_default_configurations.py
mlpipeline/_pipeline.py
mlpipeline/_pipeline_subprocess.py
mlpipeline/api.py
mlpipeline/entities.py
mlpipeline/base/__init__.py
mlpipeline/base/_base.py
mlpipeline/base/_utils.py
mlpipeline/pytorch/__init__.py
mlpipeline/pytorch/_dataloader.py
mlpipeline/pytorch/_experiment.py
mlpipeline/utils/__init__.py
mlpipeline/utils/_utils.py
mlpipeline-2.0a4.post18.dist-info/LICENSE
mlpipeline-2.0a4.post18.dist-info/METADATA
mlpipeline-2.0a4.post18.dist-info/WHEEL
mlpipeline-2.0a4.post18.dist-info/entry_points.txt
mlpipeline-2.0a4.post18.dist-info/top_level.txt
mlpipeline-2.0a4.post18.dist-info/RECORD
