Metadata-Version: 2.1
Name: mlpipeline
Version: 2.0a4.post18
Summary: A framework to define a machine learning pipeline
Home-page: https://github.com/ahmed-shariff/mlpipeline
Author: Ahmed Shariff
Author-email: shariff.mfa@outlook.com
License: UNKNOWN
Platform: UNKNOWN
Classifier: Programming Language :: Python :: 3
Classifier: Environment :: Console
Classifier: License :: OSI Approved :: MIT License
Classifier: Natural Language :: English
Classifier: Operating System :: POSIX :: Linux
Classifier: Topic :: Scientific/Engineering
Classifier: Topic :: Scientific/Engineering :: Artificial Intelligence
Requires-Dist: easydict (>=1.8)
Requires-Dist: mlflow (>=1.0.0)
